llmx/__init__.py
llmx/cli.py
llmx/datamodel.py
llmx/utils.py
llmx/version.py
llmx/configs/config.default.yml
llmx/generators/__init__.py
llmx/generators/text/__init__.py
llmx/generators/text/base_textgen.py
llmx/generators/text/cohere_textgen.py
llmx/generators/text/hf_textgen.py
llmx/generators/text/openai_textgen.py
llmx/generators/text/palm_textgen.py
llmx/generators/text/providers.py
llmx/generators/text/textgen.py
llmx-0.0.21a0.dist-info/LICENSE
llmx-0.0.21a0.dist-info/METADATA
llmx-0.0.21a0.dist-info/WHEEL
llmx-0.0.21a0.dist-info/entry_points.txt
llmx-0.0.21a0.dist-info/top_level.txt
llmx-0.0.21a0.dist-info/RECORD
