Metadata-Version: 2.1
Name: llmx
Version: 0.0.21a0
Summary: LLMX: A library for LLM Text Generation
Author-email: Victor Dibia <victor.dibia@gmail.com>
License: The MIT License (MIT)
Project-URL: Homepage, https://github.com/victordibia/llmx
Project-URL: Bug Tracker, https://github.com/victordibia/llmx/issues
Classifier: Programming Language :: Python :: 3
Classifier: License :: OSI Approved :: MIT License
Classifier: Operating System :: OS Independent
Requires-Python: >=3.9
License-File: LICENSE
Requires-Dist: pydantic
Requires-Dist: openai
Requires-Dist: tiktoken
Requires-Dist: diskcache
Requires-Dist: cohere
Requires-Dist: google.auth
Requires-Dist: typer
Requires-Dist: pyyaml
Provides-Extra: web
Requires-Dist: fastapi; extra == "web"
Requires-Dist: uvicorn; extra == "web"
Provides-Extra: transformers
Requires-Dist: transformers[torch]>=4.26; extra == "transformers"
Requires-Dist: accelerate; extra == "transformers"
